example/__init__.py
example/main.py
example/controllers/DummyCommandableHttpController.py
example/controllers/DummyRestController.py
example/controllers/__init__.py
example/data/Dummy.py
example/data/DummySchema.py
example/data/__init__.py
example/logic/DummyCommandSet.py
example/logic/DummyService.py
example/logic/IDummyService.py
example/logic/__init__.py
pip_services4_swagger/__init__.py
pip_services4_swagger/build/DefaultSwaggerFactory.py
pip_services4_swagger/build/__init__.py
pip_services4_swagger/controllers/SwaggerController.py
pip_services4_swagger/controllers/__init__.py
pip_services4_swagger/swagger-ui/favicon-16x16.png
pip_services4_swagger/swagger-ui/favicon-32x32.png
pip_services4_swagger/swagger-ui/index.html
pip_services4_swagger/swagger-ui/oauth2-redirect.html
pip_services4_swagger/swagger-ui/swagger-ui-bundle.js
pip_services4_swagger/swagger-ui/swagger-ui-bundle.js.map
pip_services4_swagger/swagger-ui/swagger-ui-es-bundle-core.js
pip_services4_swagger/swagger-ui/swagger-ui-es-bundle-core.js.map
pip_services4_swagger/swagger-ui/swagger-ui-es-bundle.js
pip_services4_swagger/swagger-ui/swagger-ui-es-bundle.js.map
pip_services4_swagger/swagger-ui/swagger-ui-standalone-preset.js
pip_services4_swagger/swagger-ui/swagger-ui-standalone-preset.js.map
pip_services4_swagger/swagger-ui/swagger-ui.css
pip_services4_swagger/swagger-ui/swagger-ui.css.map
pip_services4_swagger/swagger-ui/swagger-ui.js
pip_services4_swagger/swagger-ui/swagger-ui.js.map
pip_services4_swagger-0.0.1.dist-info/METADATA
pip_services4_swagger-0.0.1.dist-info/WHEEL
pip_services4_swagger-0.0.1.dist-info/top_level.txt
pip_services4_swagger-0.0.1.dist-info/zip-safe
pip_services4_swagger-0.0.1.dist-info/RECORD
